singledispatch/__init__.py
singledispatch-4.1.0.dist-info/LICENSE
singledispatch-4.1.0.dist-info/METADATA
singledispatch-4.1.0.dist-info/WHEEL
singledispatch-4.1.0.dist-info/top_level.txt
singledispatch-4.1.0.dist-info/RECORD
