Metadata-Version: 2.1
Name: singledispatch
Version: 4.1.0
Summary: Backport functools.singledispatch to older Pythons.
Home-page: https://github.com/jaraco/singledispatch
Author: Jason R. Coombs
Author-email: jaraco@jaraco.com
Keywords: single,dispatch,generic,functions,singledispatch,genericfunctions,decorator,backport
Classifier: Development Status :: 5 - Production/Stable
Classifier: Intended Audience :: Developers
Classifier: License :: OSI Approved :: MIT License
Classifier: Programming Language :: Python
Classifier: Programming Language :: Python :: 3
Requires-Python: >=3.8
Provides-Extra: testing
Provides-Extra: docs
License-File: LICENSE
